tsdate/__init__.py
tsdate/__main__.py
tsdate/_version.py
tsdate/accelerate.py
tsdate/approx.py
tsdate/cache.py
tsdate/cli.py
tsdate/core.py
tsdate/demography.py
tsdate/discrete.py
tsdate/evaluation.py
tsdate/hypergeo.py
tsdate/node_time_class.py
tsdate/phasing.py
tsdate/prior.py
tsdate/provenance.py
tsdate/rescaling.py
tsdate/schemas.py
tsdate/util.py
tsdate/variational.py
tsdate-0.2.4.dist-info/licenses/LICENSE
tsdate-0.2.4.dist-info/METADATA
tsdate-0.2.4.dist-info/WHEEL
tsdate-0.2.4.dist-info/entry_points.txt
tsdate-0.2.4.dist-info/top_level.txt
tsdate-0.2.4.dist-info/RECORD
